linkml_arrays/__init__.py
linkml_arrays/cli.py
linkml_arrays/dumpers/__init__.py
linkml_arrays/dumpers/hdf5_dumper.py
linkml_arrays/dumpers/yaml_hdf5_dumper.py
linkml_arrays/dumpers/yaml_numpy_dumper.py
linkml_arrays/dumpers/zarr_directory_store_dumper.py
linkml_arrays/loaders/__init__.py
linkml_arrays/loaders/hdf5_loader.py
linkml_arrays/loaders/yaml_hdf5_loader.py
linkml_arrays/loaders/yaml_numpy_loader.py
linkml_arrays/loaders/zarr_directory_store_loader.py
linkml_arrays/main.py
linkml_arrays-0.1.0.dist-info/LICENSE
linkml_arrays-0.1.0.dist-info/METADATA
linkml_arrays-0.1.0.dist-info/WHEEL
linkml_arrays-0.1.0.dist-info/entry_points.txt
linkml_arrays-0.1.0.dist-info/RECORD
